rfid_squeezectl.py
rfid_squeezectl-0.1.1.dist-info/LICENSE
rfid_squeezectl-0.1.1.dist-info/METADATA
rfid_squeezectl-0.1.1.dist-info/WHEEL
rfid_squeezectl-0.1.1.dist-info/entry_points.txt
rfid_squeezectl-0.1.1.dist-info/top_level.txt
rfid_squeezectl-0.1.1.dist-info/RECORD
